CHANGES.rst
COPYING
MANIFEST.in
README.rst
setup.cfg
setup.py
docs/Makefile
docs/conf.py
docs/index.rst
docs/make.bat
docs/_include/intro.rst
docs/api/errors.rst
docs/api/schema.rst
docs/api/validators.rst
docs/pages/changelog.rst
docs/pages/extending.rst
docs/pages/getting_started.rst
onctuous/__init__.py
onctuous/errors.py
onctuous/schema.py
onctuous/validators.py
onctuous.egg-info/PKG-INFO
onctuous.egg-info/SOURCES.txt
onctuous.egg-info/dependency_links.txt
onctuous.egg-info/not-zip-safe
onctuous.egg-info/top_level.txt
onctuous/tests/__init__.py
onctuous/tests/functional/__init__.py
onctuous/tests/functional/test_global.py
onctuous/tests/functional/test_schema.py
onctuous/tests/unittests/__init__.py
onctuous/tests/unittests/test_invalid.py
onctuous/tests/unittests/test_markers.py
onctuous/tests/unittests/test_schema.py
onctuous/tests/unittests/test_validators.py