Metadata-Version: 1.0
Name: onctuous
Version: 0.5.84
Summary: Fluid and pleasing to use data validator for Python
Home-page: https://bitbucket.org/Ludia/onctuous
Author: Jean-Tiare Le Bigot
Author-email: jtlebigot@socialludia.com
License: UNKNOWN
Keywords: validation
Platform: UNKNOWN
Classifier: Development Status :: 4 - Beta
Classifier: License :: OSI Approved :: BSD License
Classifier: Environment :: Plugins
Classifier: Intended Audience :: Developers
Classifier: Operating System :: OS Independent
Classifier: Programming Language :: Python
Classifier: Programming Language :: Python :: 2.7
Classifier: Topic :: Software Development :: Libraries :: Python Modules
Classifier: Topic :: Software Development :: Testing
